pysolace/__init__.py
pysolace/__init__.pyi
pysolace/_core.cpython-39-x86_64-linux-gnu.so
pysolace/_core.pyi
pysolace/solmsg.cpython-39-x86_64-linux-gnu.so
pysolace/solmsg.pyi
pysolace.libs/libsolclient-b1c3f942.so.1
pysolace-0.9.52.dist-info/METADATA
pysolace-0.9.52.dist-info/WHEEL
pysolace-0.9.52.dist-info/entry_points.txt
pysolace-0.9.52.dist-info/RECORD
