Metadata-Version: 2.1
Name: pysolace
Version: 0.9.52
Summary: Python client library for Solace PubSub+ event broker, enabling easy integration for messaging applications.
Keywords: solace,pubsub+,messaging,event broker,queue,topic,publish,subscribe
Author-Email: yvictor <yvictor3141@gmail.com>
Classifier: Development Status :: 4 - Beta
Classifier: Intended Audience :: Developers
Classifier: Topic :: Software Development :: Libraries :: Python Modules
Classifier: Topic :: System :: Networking
Classifier: Topic :: Communications
Classifier: Programming Language :: Python :: 3
Classifier: Programming Language :: Python :: 3.7
Classifier: Programming Language :: Python :: 3.8
Classifier: Programming Language :: Python :: 3.9
Classifier: Programming Language :: Python :: 3.10
Classifier: Programming Language :: Python :: 3.11
Classifier: Programming Language :: Python :: 3.12
Classifier: Programming Language :: Python :: 3.13
Classifier: Programming Language :: C++
Classifier: Operating System :: MacOS
Classifier: Operating System :: POSIX :: Linux
Classifier: Operating System :: Microsoft :: Windows
Project-URL: Homepage, https://github.com/yvictor/pysolace
Project-URL: Repository, https://github.com/yvictor/pysolace
Requires-Python: >=3.6
Requires-Dist: loguru>=0.6.0
Requires-Dist: msgpack>=1.0.3
Requires-Dist: orjson>=3.3.1
Requires-Dist: typer>=0.10.0
